_portaudio.cp36-win32.pyd
pyaudio.py
PyAudio-0.2.10.dist-info/DESCRIPTION.rst
PyAudio-0.2.10.dist-info/METADATA
PyAudio-0.2.10.dist-info/RECORD
PyAudio-0.2.10.dist-info/WHEEL
PyAudio-0.2.10.dist-info/metadata.json
PyAudio-0.2.10.dist-info/top_level.txt
