Metadata-Version: 2.0
Name: PyAudio
Version: 0.2.10
Summary: PortAudio Python Bindings
Home-page: http://people.csail.mit.edu/hubert/pyaudio/
Author: Hubert Pham
Author-email: UNKNOWN
License: UNKNOWN
Platform: UNKNOWN
